setup.py
snsg/__init__.py
snsg/mate.py
snsg/snsg.py
snsg.egg-info/PKG-INFO
snsg.egg-info/SOURCES.txt
snsg.egg-info/dependency_links.txt
snsg.egg-info/top_level.txt