Metadata-Version: 1.1
Name: snsg
Version: 1.8.16
Summary: this is a train text code
Home-page: https://gitee.com/tyoui/snsg
Author: tyoui
Author-email: tyoui@tyoui.cn
License: UNKNOWN
Download-URL: https://gitee.com/tyoui/snsg.git
Platform: any
